craftainer/__init__.py
craftainer/__main__.py
craftainer/craftainer.py
craftainer-0.1.0.dist-info/METADATA
craftainer-0.1.0.dist-info/WHEEL
craftainer-0.1.0.dist-info/entry_points.txt
craftainer-0.1.0.dist-info/RECORD
