Metadata-Version: 2.3
Name: craftainer
Version: 0.1.0
Summary: Add your description here
Author-email: todo <todo@todo.todo>
Requires-Python: >=3.10
Requires-Dist: docker>=7.1.0
Requires-Dist: pydantic>=2.11.7
Requires-Dist: questionary>=2.1.0
Requires-Dist: typer>=0.16.0
